Skydipper/Skydipper.py
Skydipper/__init__.py
Skydipper/collection.py
Skydipper/dataset.py
Skydipper/geometry.py
Skydipper/image.py
Skydipper/imageCollection.py
Skydipper/layer.py
Skydipper/lmipy.py
Skydipper/table.py
Skydipper/user.py
Skydipper/utils.py
Skydipper-0.2.6.dist-info/LICENSE
Skydipper-0.2.6.dist-info/METADATA
Skydipper-0.2.6.dist-info/WHEEL
Skydipper-0.2.6.dist-info/top_level.txt
Skydipper-0.2.6.dist-info/RECORD
