Metadata-Version: 2.1
Name: Skydipper
Version: 0.2.6
Summary: Pythonic interface to the Skydipper API.
Home-page: https://github.com/Skydipper/Skydipper
Author: Vizzuality
Author-email: benjamin.laken@vizzuality.com
License: MIT
Platform: UNKNOWN
Classifier: Programming Language :: Python :: 3
Classifier: Programming Language :: Python :: 3.7
Classifier: License :: OSI Approved :: MIT License
Classifier: Operating System :: OS Independent
Requires-Dist: requests (>=2.2.0)
Requires-Dist: folium (==0.8.3)
Requires-Dist: google-cloud-storage
Requires-Dist: earthengine-api (==0.1.215)
Requires-Dist: geopandas (>=0.4.1)
Requires-Dist: geojson (>=2.4.0)
Requires-Dist: pypng (>=0.0.19)
Requires-Dist: tqdm (==4.41.1)
